ani_file/__init__.py
ani_file/ani_file.py
ani_file-0.1.3.dist-info/METADATA
ani_file-0.1.3.dist-info/WHEEL
ani_file-0.1.3.dist-info/licenses/LICENSE
ani_file-0.1.3.dist-info/RECORD
