Metadata-Version: 2.1
Name: ani_file
Version: 0.1.3
Summary: ani file reader and writer
Project-URL: Homepage, https://github.com/HoangEevee/ani_file
Author-email: HoangEevee <nguyenquochoang2806@gmail.com>
License: MIT License
License-File: LICENSE
Classifier: License :: OSI Approved :: MIT License
Classifier: Operating System :: OS Independent
Classifier: Programming Language :: Python :: 3
Requires-Python: >=3.7
